chasca/__init__.py
chasca/chasca.py
chasca-0.3.dist-info/LICENSE
chasca-0.3.dist-info/METADATA
chasca-0.3.dist-info/WHEEL
chasca-0.3.dist-info/top_level.txt
chasca-0.3.dist-info/RECORD
