Metadata-Version: 2.1
Name: chasca
Version: 0.3
Summary: Tools to plan astronomical observations
Home-page: https://github.com/ramstojh/chasca
Author: Jhon Yana
Author-email: ramstojh@alumni.usp.br
License: MIT
License-File: LICENSE
